fluorseg/__init__.py
fluorseg/filebrowser.py
fluorseg/liffile.py
fluorseg/methods.py
fluorseg/reports.py
fluorseg/roifile.py
fluorseg/test/__init__.py
fluorseg/test/test_liffile.py
fluorseg/test/test_methods.py
FluorSeg-0.0.26.dev0.dist-info/LICENSE.txt
FluorSeg-0.0.26.dev0.dist-info/METADATA
FluorSeg-0.0.26.dev0.dist-info/WHEEL
FluorSeg-0.0.26.dev0.dist-info/top_level.txt
FluorSeg-0.0.26.dev0.dist-info/RECORD
