Metadata-Version: 2.1
Name: FluorSeg
Version: 0.0.26.dev0
Summary: Segment regions from fluorescence images
Home-page: https://github.com/TeamMacLean/fluorseg
Author: Dan MacLean
Author-email: dan.maclean@tsl.ac.uk
License: LICENSE.txt
Platform: UNKNOWN
Requires-Python: >=3.6.7
Requires-Dist: javabridge (>=1.0.14)
Requires-Dist: python-bioformats (>=1.5.2)
Requires-Dist: matplotlib (>=3.0.1)
Requires-Dist: numpy (>=1.5.3)
Requires-Dist: read-roi (>=1.4.2)
Requires-Dist: pillow (>=5.3.0)
Requires-Dist: scipy (>=1.1.0)
Requires-Dist: scikit-image (>=0.14.1)
